HoloWave/HoloWave.py
HoloWave/__init__.py
holowave-0.1.1.dist-info/METADATA
holowave-0.1.1.dist-info/WHEEL
holowave-0.1.1.dist-info/top_level.txt
holowave-0.1.1.dist-info/RECORD
