Metadata-Version: 2.4
Name: HoloWave
Version: 0.1.1
Summary: Modern Sound manager for modern AI-driven applications.
Author: Tristan McBride Sr.
Author-email: "Tristan McBride Sr." <142635792+TristanMcBrideSr@users.noreply.github.com>
Maintainer-email: "Tristan McBride Sr." <142635792+TristanMcBrideSr@users.noreply.github.com>
License-Expression: Apache-2.0
Project-URL: Homepage, https://github.com/TristanMcBrideSr
Keywords: AI,Agents,Speech Recognition,Productivity,Automation
Classifier: Programming Language :: Python :: 3
Classifier: Operating System :: OS Independent
Classifier: Intended Audience :: Developers
Requires-Python: >=3.10
Requires-Dist: pygame
Dynamic: author
